st/__init__.py
st/bin/__main__.py
st/icons/about.png
st/icons/code.png
st/icons/editor.png
st/icons/exit.png
st/icons/merge.png
st/icons/notebook.png
st/icons/read.png
st/icons/sih.png
st/icons/split.png
st/icons/write.png
st/widgets/CodeEditor.py
st/widgets/ExcelReader.py
st/widgets/ExcelWriter.py
st/widgets/Home.py
st/widgets/Main.py
st/widgets/Merger.py
st/widgets/Splitter.py
st/widgets/Viewer.py
st/widgets/__init__.py
spreadsheet_tools-0.0.1.dist-info/LICENSE
spreadsheet_tools-0.0.1.dist-info/METADATA
spreadsheet_tools-0.0.1.dist-info/WHEEL
spreadsheet_tools-0.0.1.dist-info/entry_points.txt
spreadsheet_tools-0.0.1.dist-info/top_level.txt
spreadsheet_tools-0.0.1.dist-info/RECORD
