Metadata-Version: 2.1
Name: spreadsheet-tools
Version: 0.0.1
Summary: All-in-one spreadsheet tools.
Home-page: https://github.com/fatihmete/spreadsheet-tools
Author: Fatih Mete
Author-email: fatihmete@live.com
License: UNKNOWN
Platform: UNKNOWN
Classifier: Programming Language :: Python :: 3
Classifier: License :: OSI Approved :: MIT License
Classifier: Operating System :: OS Independent
Requires-Python: >=3.6
Requires-Dist: pandas (>=1.1.0)
Requires-Dist: openpyxl (>=3.0.5)
Requires-Dist: PyQt5-sip (>=12.8.1)
Requires-Dist: PyQt5 (>=5.15.1)
Requires-Dist: numpy (>=1.19.3)
